repos_cli/__init__.py
repos_cli/cli.py
repos_cli/config.py
repos_cli/db.py
repos_cli/executor.py
repos_cli/init.py
repos_cli/interfaces.py
repos_cli/kernel.py
repos_cli/store.py
repos_cli/ui.py
repos_cli/utils.py
repos_cli/defaults/__init__.py
repos_cli/defaults/conda.yaml
repos_cli/defaults/docker.yaml
repos_cli/defaults/git.yaml
repos_cli/defaults/node.yaml
repos_cli/defaults/os.yaml
repos_cli/defaults/python.yaml
repos_cli/defaults/ruby.yaml
repos_cli/defaults/system.yaml
repos_cli-0.0.4.dist-info/licenses/LICENSE
repos_cli-0.0.4.dist-info/licenses/NOTICE
repos_cli-0.0.4.dist-info/METADATA
repos_cli-0.0.4.dist-info/WHEEL
repos_cli-0.0.4.dist-info/entry_points.txt
repos_cli-0.0.4.dist-info/top_level.txt
repos_cli-0.0.4.dist-info/RECORD
