Metadata-Version: 2.4
Name: repos-cli
Version: 0.0.4
Summary: RepOS - REPL-driven developer operating system
Author: TriFactoria (Andrew Blankfield)
License-Expression: LicenseRef-RepOS-BSL-1.1
Project-URL: Homepage, https://github.com/TriFactoria/repos-cli
Project-URL: Repository, https://github.com/TriFactoria/repos-cli
Project-URL: Issues, https://github.com/TriFactoria/repos-cli/issues
Classifier: Development Status :: 3 - Alpha
Classifier: Programming Language :: Python :: 3
Classifier: Operating System :: POSIX :: Linux
Requires-Python: >=3.10
License-File: LICENSE
License-File: NOTICE
Requires-Dist: prompt-toolkit>=3.0.0
Requires-Dist: PyYAML>=6.0.0
Provides-Extra: dev
Requires-Dist: pytest>=7; extra == "dev"
Requires-Dist: build>=1; extra == "dev"
Requires-Dist: twine>=5; extra == "dev"
Requires-Dist: black>=24; extra == "dev"
Requires-Dist: ruff>=0.8; extra == "dev"
Dynamic: license-file
